trajMap/__init__.py
trajMap/main.py
trajMap/datasets/trajMap_reference_1.h5ad
trajMap/datasets/variable_2000.csv
trajMap/datasets/pseduoPred/fingerprint.pb
trajMap/datasets/pseduoPred/keras_metadata.pb
trajMap/datasets/pseduoPred/saved_model.pb
trajMap/datasets/pseduoPred/variables/variables.data-00000-of-00001
trajMap/datasets/pseduoPred/variables/variables.index
trajMap/datasets/scanvi_chondro/model.pt
trajMap/datasets/scanvi_lepr/model.pt
trajMap/datasets/scanvi_mes/model.pt
trajMap-0.1.0.dist-info/LICENSE
trajMap-0.1.0.dist-info/METADATA
trajMap-0.1.0.dist-info/WHEEL
trajMap-0.1.0.dist-info/top_level.txt
trajMap-0.1.0.dist-info/RECORD
