Metadata-Version: 2.1
Name: trajMap
Version: 0.1.0
Summary: trajMap test
Author-email: Gilbert Han <gilberthan1011@gmail.com>
Project-URL: Homepage, https://github.com/GilbertHan1011/Macro_osteo_comm
Project-URL: Bug Tracker, https://github.com/GilbertHan1011/Macro_osteo_comm/issues
Classifier: Programming Language :: Python :: 3
Classifier: License :: OSI Approved :: MIT License
Classifier: Operating System :: OS Independent
Requires-Python: >=3.9
License-File: LICENSE
Requires-Dist: anndata (>=0.8.0)
Requires-Dist: numpy (>=1.23.5)
Requires-Dist: scipy (>=1.9.3)
Requires-Dist: joblib (>=1.2.0)
Requires-Dist: pandas (==1.5.3)
Requires-Dist: scvi (>=0.6.8)
Requires-Dist: scarches (>=0.5.6)
Requires-Dist: tensorflow (>=2.11.0)
Requires-Dist: scanpy (>=1.9.1)
